{"name":"Kommuki PYT! Kamen 2024","spaltennamen":{"is_ok":true,"glues":{}},"werte":{"check_jahr":{"is_ok":true,"glues":"Werte für diese Variable: 2024","spaltenname":"Jahr"},"check_ausschuss":{"is_ok":true,"glues":{},"spaltenname":"Ausschuss"},"check_im_ausschuss_genehmigt":{"is_ok":true,"glues":{},"spaltenname":"im Ausschuss genehmigt"},"check_im_rat_genehmigt":{"is_ok":true,"glues":{},"spaltenname":"im Rat genehmigt"},"check_einwohnerzahl":{"is_ok":true,"glues":"Werte für diese Variable: 43058","spaltenname":"Einwohnerzahl"},"check_staerkste_fraktion":{"is_ok":true,"glues":"Werte für diese Variable: SPD","spaltenname":"stärkste Fraktion"},"check_schulform":{"is_ok":true,"glues":{},"spaltenname":"Schulform"},"check_urban_laendlich":{"is_ok":true,"glues":{},"spaltenname":"urban/ländlich"},"check_bundesland":{"is_ok":true,"glues":{},"spaltenname":"Bundesland"},"check_status_echt":{"is_ok":true,"glues":{},"spaltenname":"Status in echt"}}}
